{
	"format_version": "1.10.0",
	"animation_controllers": {
		"controller.animation.tosca": {
			"states": {
				"default": {
					"transitions": [
						{
							"tosca_normal": "q.skin_id == 0"
						},
						{
							"back_mirror_open": "q.skin_id == 1"
						},
						{
							"back_mirror_close": "q.skin_id == 2"
						},
						{
							"light_on": "q.skin_id == 3"
						},
						{
							"light_off": "q.skin_id == 4"
						},
						{
							"left_signal": "q.skin_id == 5"
						},
						{
							"right_signal": "q.skin_id == 6"
						},
						{
							"right_front_door_open": "q.skin_id == 7"
						},
						{
							"right_front_door_close": "q.skin_id == 8"
						},
						{
							"roll_up": "q.skin_id == 9"
						},
						{
							"roll_down": "q.skin_id == 10"
						},
						{
							"right_second_door_open": "q.skin_id == 11"
						},
						{
							"right_second_door_close": "q.skin_id == 12"
						},
						{
							"left_front_door_open": "q.skin_id == 13"
						},
						{
							"left_front_door_close": "q.skin_id == 14"
						},
						{
							"left_second_door_open": "q.skin_id == 15"
						},
						{
							"left_second_door_close": "q.skin_id == 16"
						},
						{
							"bonnet_open": "q.skin_id == 17"
						},
						{
							"bonnet_close": "q.skin_id == 18"
						},
						{
							"pedal": "q.skin_id == 19"
						},
						{
							"key": "q.skin_id == 20"
						}
					]
				},
				"tosca_normal": {
					"transitions": [
						{
							"default": "q.skin_id != 0"
						}
					],
					"on_entry": [
					]
				},
				"back_mirror_open": {
					"transitions": [
						{
							"default": "q.skin_id != 1"
						}
					],
					"on_entry": [
					]
				},
				"back_mirror_close": {
					"transitions": [
						{
							"default": "q.skin_id != 2"
						}
					],
					"on_entry": [
					]
				},
				"light_on": {
					"transitions": [
						{
							"default": "q.skin_id != 3"
						}
					],
					"on_entry": [
					]
				},
				"light_off": {
					"transitions": [
						{
							"default": "q.skin_id != 4"
						}
					],
					"on_entry": [
					]
				},
				"left_signal": {
					"transitions": [
						{
							"default": "q.skin_id != 5"
						}
					],
					"on_entry": [
					]
				},
				"right_signal": {
					"transitions": [
						{
							"default": "q.skin_id != 6"
						}
					],
					"on_entry": [
					]
				},
				"right_front_door_open": {
					"transitions": [
						{
							"default": "q.skin_id != 7"
						}
					],
					"on_entry": [
					]
				},
				"right_front_door_close": {
					"transitions": [
						{
							"default": "q.skin_id != 8"
						}
					],
					"on_entry": [
					]
				},
				"roll_up": {
					"transitions": [
						{
							"default": "q.skin_id != 9"
						}
					],
					"on_entry": [
					]
				},
				"roll_down": {
					"transitions": [
						{
							"default": "q.skin_id != 10"
						}
					],
					"on_entry": [
					]
				},
				"right_second_door_open": {
					"transitions": [
						{
							"default": "q.skin_id != 11"
						}
					],
					"on_entry": [
					]
				},
				"right_second_door_close": {
					"transitions": [
						{
							"default": "q.skin_id != 12"
						}
					],
					"on_entry": [
					]
				},
				"left_front_door_open": {
					"transitions": [
						{
							"default": "q.skin_id != 13"
						}
					],
					"on_entry": [
					]
				},
				"left_front_door_close": {
					"transitions": [
						{
							"default": "q.skin_id != 14"
						}
					],
					"on_entry": [
					]
				},
				"left_second_door_open": {
					"transitions": [
						{
							"default": "q.skin_id != 15"
						}
					],
					"on_entry": [
					]
				},
				"left_second_door_close": {
					"transitions": [
						{
							"default": "q.skin_id != 16"
						}
					],
					"on_entry": [
					]
				},
				"bonnet_open": {
					"transitions": [
						{
							"default": "q.skin_id != 17"
						}
					],
					"on_entry": [
					]
				},
				"bonnet_close": {
					"transitions": [
						{
							"default": "q.skin_id != 18"
						}
					],
					"on_entry": [
					]
				},
				"pedal": {
					"transitions": [
						{
							"default": "q.skin_id != 19"
						}
					],
					"on_entry": [
					]
				},
				"key": {
					"transitions": [
						{
							"default": "q.skin_id != 20"
						}
					],
					"on_entry": [
					]
				}
			}
		}
	}
}